hhcn10/hhcn10.py
python_hhc_n10-0.0.1.dist-info/METADATA
python_hhc_n10-0.0.1.dist-info/WHEEL
python_hhc_n10-0.0.1.dist-info/top_level.txt
python_hhc_n10-0.0.1.dist-info/RECORD
