Metadata-Version: 2.1
Name: python-hhc-n10
Version: 0.0.1
Summary: Interfaces with HHC-N10 (Ethernet Relay)
Home-page: http://github.com/Frankkkkk/python-hhc-n10
Author: Frank Villaro-Dixon
Author-email: frank@villaro-dixon.eu
License: MIT
Keywords: ethernet relay hhc-n10
Classifier: Development Status :: 3 - Alpha
Classifier: Topic :: Utilities
Classifier: License :: OSI Approved :: MIT License
